python_lnd_grpc/__init__.py
python_lnd_grpc/lnd_defaults.py
python_lnd_grpc/python_lnd_grpc.py
python_lnd_grpc/protos/autopilot.proto
python_lnd_grpc/protos/autopilot_pb2.py
python_lnd_grpc/protos/autopilot_pb2_grpc.py
python_lnd_grpc/protos/chainnotifier.proto
python_lnd_grpc/protos/chainnotifier_pb2.py
python_lnd_grpc/protos/chainnotifier_pb2_grpc.py
python_lnd_grpc/protos/invoices.proto
python_lnd_grpc/protos/invoices_pb2.py
python_lnd_grpc/protos/invoices_pb2_grpc.py
python_lnd_grpc/protos/lncli.proto
python_lnd_grpc/protos/proto_download.py
python_lnd_grpc/protos/rpc.proto
python_lnd_grpc/protos/rpc_pb2.py
python_lnd_grpc/protos/rpc_pb2_grpc.py
python_lnd_grpc/protos/signer.proto
python_lnd_grpc/protos/signer_pb2.py
python_lnd_grpc/protos/signer_pb2_grpc.py
python_lnd_grpc/protos/versioner.proto
python_lnd_grpc/protos/versioner_pb2.py
python_lnd_grpc/protos/versioner_pb2_grpc.py
python_lnd_grpc/protos/walletkit.proto
python_lnd_grpc/protos/walletunlocker.proto
python_lnd_grpc/protos/walletunlocker_pb2.py
python_lnd_grpc/protos/walletunlocker_pb2_grpc.py
python_lnd_grpc/protos/watchtower.proto
python_lnd_grpc/protos/watchtower_pb2.py
python_lnd_grpc/protos/watchtower_pb2_grpc.py
python_lnd_grpc/protos/wtclient.proto
python_lnd_grpc/protos/wtclient_pb2.py
python_lnd_grpc/protos/wtclient_pb2_grpc.py
python_lnd_grpc-0.0.8.5.dist-info/DESCRIPTION.rst
python_lnd_grpc-0.0.8.5.dist-info/METADATA
python_lnd_grpc-0.0.8.5.dist-info/RECORD
python_lnd_grpc-0.0.8.5.dist-info/WHEEL
python_lnd_grpc-0.0.8.5.dist-info/metadata.json
python_lnd_grpc-0.0.8.5.dist-info/top_level.txt
